task_flows/__init__.py
task_flows/admin.py
task_flows/schedule.py
task_flows/utils.py
task_flows/database/__init__.py
task_flows/database/core.py
task_flows/database/tables.py
task_flows/docker/__init__.py
task_flows/docker/container.py
task_flows/docker/image.py
task_flows/docker/utils.py
task_flows/systemd/__init__.py
task_flows/systemd/core.py
task_flows/systemd/models.py
task_flows/systemd/templates/__init__.py
task_flows/systemd/templates/service.jinja2
task_flows/systemd/templates/timer.jinja2
task_flows/tasks/__init__.py
task_flows/tasks/decorators.py
task_flows/tasks/logger.py
task_flows-0.3.3.dist-info/METADATA
task_flows-0.3.3.dist-info/WHEEL
task_flows-0.3.3.dist-info/entry_points.txt
task_flows-0.3.3.dist-info/top_level.txt
task_flows-0.3.3.dist-info/RECORD
