Metadata-Version: 2.1
Name: task-flows
Version: 0.3.3
Summary: Python task management, scheduling, alerts.
Author-email: Dan Kelleher <kelleherjdan@gmail.com>
License: MIT
Classifier: License :: OSI Approved :: MIT License
Classifier: Programming Language :: Python
Classifier: Programming Language :: Python :: 3
Requires-Dist: sqlalchemy >=2.0.0
Requires-Dist: docker
Requires-Dist: tqdm
Requires-Dist: click
Requires-Dist: psycopg[c] >=3.0.0
Requires-Dist: python-dotenv
Requires-Dist: xxhash
Requires-Dist: paramiko
Requires-Dist: rich
Requires-Dist: python-dateutil
Requires-Dist: jinja2
Requires-Dist: dynamic-imports >=1.0.0
Requires-Dist: alert-msgs >=0.2.0
Requires-Dist: ezloggers >=1.1.0
Requires-Dist: func-timeout >=4.0.0
Provides-Extra: dev
Requires-Dist: black ; extra == 'dev'
Requires-Dist: pytest ; extra == 'dev'
